MANIFEST.in
setup.py
docs/CONTRIBUTORS.txt
docs/HISTORY.txt
docs/LICENSE.ZPL
docs/LICENSE.txt
docs/README.txt
src/ztfy/__init__.py
src/ztfy.appskin.egg-info/PKG-INFO
src/ztfy.appskin.egg-info/SOURCES.txt
src/ztfy.appskin.egg-info/dependency_links.txt
src/ztfy.appskin.egg-info/entry_points.txt
src/ztfy.appskin.egg-info/namespace_packages.txt
src/ztfy.appskin.egg-info/not-zip-safe
src/ztfy.appskin.egg-info/requires.txt
src/ztfy.appskin.egg-info/top_level.txt
src/ztfy/appskin/__init__.py
src/ztfy/appskin/batch.py
src/ztfy/appskin/configure.zcml
src/ztfy/appskin/interfaces.py
src/ztfy/appskin/layer.py
src/ztfy/appskin/login.py
src/ztfy/appskin/doctests/README.txt
src/ztfy/appskin/locales/ztfy.appskin.pot
src/ztfy/appskin/locales/en/LC_MESSAGES/ztfy.appskin.mo
src/ztfy/appskin/locales/en/LC_MESSAGES/ztfy.appskin.po
src/ztfy/appskin/locales/en/LC_MESSAGES/ztfy.appskin.po~
src/ztfy/appskin/locales/fr/LC_MESSAGES/ztfy.appskin.mo
src/ztfy/appskin/locales/fr/LC_MESSAGES/ztfy.appskin.po
src/ztfy/appskin/locales/fr/LC_MESSAGES/ztfy.appskin.po~
src/ztfy/appskin/resources/css/ztfy.appskin.css
src/ztfy/appskin/resources/css/ztfy.appskin.grey.css
src/ztfy/appskin/resources/css/ztfy.appskin.grey.min.css
src/ztfy/appskin/resources/css/ztfy.appskin.min.css
src/ztfy/appskin/resources/img/breadcrumb.png
src/ztfy/appskin/resources/img/menu-active.png
src/ztfy/appskin/resources/js/ztfy.appskin.js
src/ztfy/appskin/resources/js/ztfy.appskin.min.js
src/ztfy/appskin/tal/__init__.py
src/ztfy/appskin/tal/api.py
src/ztfy/appskin/tal/configure.zcml
src/ztfy/appskin/tal/interfaces.py
src/ztfy/appskin/templates/anonymous_layout.pt
src/ztfy/appskin/templates/display-form.pt
src/ztfy/appskin/templates/inner_list.pt
src/ztfy/appskin/templates/layout.pt
src/ztfy/appskin/tests/__init__.py
src/ztfy/appskin/tests/test_docs.py
src/ztfy/appskin/tests/test_docstrings.py
src/ztfy/appskin/viewlets/__init__.py
src/ztfy/appskin/viewlets/configure.zcml
src/ztfy/appskin/viewlets/actions/__init__.py
src/ztfy/appskin/viewlets/actions/configure.zcml
src/ztfy/appskin/viewlets/actions/interfaces.py
src/ztfy/appskin/viewlets/actions/templates/action.pt
src/ztfy/appskin/viewlets/sidebar/__init__.py
src/ztfy/appskin/viewlets/sidebar/configure.zcml
src/ztfy/appskin/viewlets/sidebar/interfaces.py
