Metadata-Version: 1.1
Name: ztfy.appskin
Version: 0.3.7
Summary: ZTFY application base skin
Home-page: http://hg.ztfy.org/ztfy.appskin
Author: Thierry Florac
Author-email: tflorac@ulthar.net
License: zpl
Keywords: ZTFY application skin
Platform: UNKNOWN
Classifier: Development Status :: 4 - Beta
Classifier: Framework :: Zope3
Classifier: Intended Audience :: Developers
Classifier: License :: OSI Approved :: Zope Public License
Classifier: Programming Language :: Python
Classifier: Topic :: Software Development :: User Interfaces
